jmvbd.py
jmvdb/__init__.py
jmvbd-2.0.1.dist-info/METADATA
jmvbd-2.0.1.dist-info/WHEEL
jmvbd-2.0.1.dist-info/entry_points.txt
jmvbd-2.0.1.dist-info/top_level.txt
jmvbd-2.0.1.dist-info/RECORD
