Metadata-Version: 2.1
Name: jmvbd
Version: 2.0.1
Summary: Jellyfin Movie Video Backdrop Downloader
Home-page: https://github.com/nxllxvxxd/JMVBD
Author: Cody St Pierre
Author-email: codystpierre0@gmail.com
Requires-Dist: requests
Requires-Dist: yt-dlp
